bigtree_config/__init__.py
bigtree_config/backends.py
bigtree_config/models.py
bigtree_config-0.0.1.dist-info/DESCRIPTION.rst
bigtree_config-0.0.1.dist-info/METADATA
bigtree_config-0.0.1.dist-info/RECORD
bigtree_config-0.0.1.dist-info/WHEEL
bigtree_config-0.0.1.dist-info/metadata.json
bigtree_config-0.0.1.dist-info/top_level.txt
