Metadata-Version: 2.0
Name: bigtree-config
Version: 0.0.1
Summary: bigtree online config. 
Home-page: http://www.hshl.ltd
Author: bigtiger
Author-email: chinafengheping@gmail.com
License: UNKNOWN
Platform: UNKNOWN
Requires-Dist: bigtree-api (>=0.0.1)
